sarvamai/__init__.py
sarvamai/chat/__init__.py
sarvamai/chat/client.py
sarvamai/chat/raw_client.py
sarvamai/client.py
sarvamai/core/__init__.py
sarvamai/core/api_error.py
sarvamai/core/client_wrapper.py
sarvamai/core/datetime_utils.py
sarvamai/core/events.py
sarvamai/core/file.py
sarvamai/core/force_multipart.py
sarvamai/core/http_client.py
sarvamai/core/http_response.py
sarvamai/core/jsonable_encoder.py
sarvamai/core/pydantic_utilities.py
sarvamai/core/query_encoder.py
sarvamai/core/remove_none_from_dict.py
sarvamai/core/request_options.py
sarvamai/core/serialization.py
sarvamai/environment.py
sarvamai/errors/__init__.py
sarvamai/errors/bad_request_error.py
sarvamai/errors/forbidden_error.py
sarvamai/errors/internal_server_error.py
sarvamai/errors/service_unavailable_error.py
sarvamai/errors/too_many_requests_error.py
sarvamai/errors/unprocessable_entity_error.py
sarvamai/play.py
sarvamai/py.typed
sarvamai/requests/__init__.py
sarvamai/requests/audio_data.py
sarvamai/requests/audio_message.py
sarvamai/requests/audio_output.py
sarvamai/requests/audio_output_data.py
sarvamai/requests/base_job_parameters.py
sarvamai/requests/bulk_job_callback.py
sarvamai/requests/bulk_job_init_response_v_1.py
sarvamai/requests/chat_completion_request_assistant_message.py
sarvamai/requests/chat_completion_request_message.py
sarvamai/requests/chat_completion_request_system_message.py
sarvamai/requests/chat_completion_request_user_message.py
sarvamai/requests/chat_completion_response_message.py
sarvamai/requests/choice.py
sarvamai/requests/completion_usage.py
sarvamai/requests/config_message.py
sarvamai/requests/configure_connection.py
sarvamai/requests/configure_connection_data.py
sarvamai/requests/create_chat_completion_response.py
sarvamai/requests/diarized_entry.py
sarvamai/requests/diarized_transcript.py
sarvamai/requests/error_data.py
sarvamai/requests/error_details.py
sarvamai/requests/error_message.py
sarvamai/requests/error_response.py
sarvamai/requests/error_response_data.py
sarvamai-0.1.19.dist-info/METADATA
sarvamai-0.1.19.dist-info/WHEEL
sarvamai-0.1.19.dist-info/RECORD
